scrapetools/__init__.py
scrapetools/email_scraper.py
scrapetools/input_scraper.py
scrapetools/link_scraper.py
scrapetools/phone_scraper.py
scrapetools/py.typed
scrapetools-1.1.9.dist-info/METADATA
scrapetools-1.1.9.dist-info/WHEEL
scrapetools-1.1.9.dist-info/licenses/LICENSE.txt
scrapetools-1.1.9.dist-info/RECORD
