Metadata-Version: 2.3
Name: scrapetools
Version: 1.1.9
Summary: A collection of tools to aid in web scraping.
Project-URL: Homepage, https://github.com/matt-manes/scrapetools
Project-URL: Documentation, https://github.com/matt-manes/scrapetools/tree/main/docs
Project-URL: Source code, https://github.com/matt-manes/scrapetools/tree/main/src/scrapetools
Author-email: Matt Manes <mattmanes@pm.me>
License-File: LICENSE.txt
Keywords: email,html,scrape,scraping,web,webscraping
Classifier: License :: OSI Approved :: MIT License
Classifier: Operating System :: OS Independent
Classifier: Programming Language :: Python :: 3
Requires-Python: >=3.10
Requires-Dist: beautifulsoup4
Requires-Dist: phonenumbers
